odoo8_addon_runbot_gitlab-8.0.1.1.0.99.dev23-py2.7-nspkg.pth
odoo8_addon_runbot_gitlab-8.0.1.1.0.99.dev23.dist-info/DESCRIPTION.rst
odoo8_addon_runbot_gitlab-8.0.1.1.0.99.dev23.dist-info/METADATA
odoo8_addon_runbot_gitlab-8.0.1.1.0.99.dev23.dist-info/RECORD
odoo8_addon_runbot_gitlab-8.0.1.1.0.99.dev23.dist-info/WHEEL
odoo8_addon_runbot_gitlab-8.0.1.1.0.99.dev23.dist-info/metadata.json
odoo8_addon_runbot_gitlab-8.0.1.1.0.99.dev23.dist-info/namespace_packages.txt
odoo8_addon_runbot_gitlab-8.0.1.1.0.99.dev23.dist-info/top_level.txt
odoo_addons/runbot_gitlab/README.rst
odoo_addons/runbot_gitlab/__init__.py
odoo_addons/runbot_gitlab/__openerp__.py
odoo_addons/runbot_gitlab/controllers/__init__.py
odoo_addons/runbot_gitlab/controllers/main.py
odoo_addons/runbot_gitlab/models/__init__.py
odoo_addons/runbot_gitlab/models/runbot_branch.py
odoo_addons/runbot_gitlab/models/runbot_build.py
odoo_addons/runbot_gitlab/models/runbot_repo.py
odoo_addons/runbot_gitlab/static/description/icon.png
odoo_addons/runbot_gitlab/static/src/img/gitlab_logo.png
odoo_addons/runbot_gitlab/views/runbot_branch.xml
odoo_addons/runbot_gitlab/views/runbot_build.xml
odoo_addons/runbot_gitlab/views/runbot_repo.xml
