Metadata-Version: 2.0
Name: odoo8-addon-runbot-gitlab
Version: 8.0.1.1.0.99.dev23
Summary: Runbot with Gitlab integration
Home-page: UNKNOWN
Author: Savoir-faire Linux,Therp BV,Odoo Community Association (OCA)
Author-email: support@odoo-community.org
License: UNKNOWN
Platform: UNKNOWN
Classifier: Programming Language :: Python
Classifier: Framework :: Odoo
Requires-Python: ~=2.7
Requires-Dist: odoo (<9.0a,>=8.0a)
Requires-Dist: odoo8-addon-runbot
Requires-Dist: requests
